odoo/addons/shopfloor_example/README.rst
odoo/addons/shopfloor_example/__init__.py
odoo/addons/shopfloor_example/__manifest__.py
odoo/addons/shopfloor_example/hooks.py
odoo/addons/shopfloor_example/actions/__init__.py
odoo/addons/shopfloor_example/actions/data.py
odoo/addons/shopfloor_example/actions/data_detail.py
odoo/addons/shopfloor_example/actions/schema.py
odoo/addons/shopfloor_example/actions/schema_detail.py
odoo/addons/shopfloor_example/actions/search.py
odoo/addons/shopfloor_example/components/__init__.py
odoo/addons/shopfloor_example/components/scan_handler_partner.py
odoo/addons/shopfloor_example/demo/shopfloor_app_demo.xml
odoo/addons/shopfloor_example/demo/shopfloor_menu_demo.xml
odoo/addons/shopfloor_example/demo/shopfloor_profile_demo.xml
odoo/addons/shopfloor_example/demo/shopfloor_scenario_demo.xml
odoo/addons/shopfloor_example/i18n/es_AR.po
odoo/addons/shopfloor_example/i18n/it.po
odoo/addons/shopfloor_example/i18n/pt_BR.po
odoo/addons/shopfloor_example/i18n/shopfloor_example.pot
odoo/addons/shopfloor_example/models/__init__.py
odoo/addons/shopfloor_example/models/shopfloor_app.py
odoo/addons/shopfloor_example/readme/CONTRIBUTORS.md
odoo/addons/shopfloor_example/readme/CREDITS.md
odoo/addons/shopfloor_example/readme/DESCRIPTION.md
odoo/addons/shopfloor_example/readme/HISTORY.md
odoo/addons/shopfloor_example/readme/ROADMAP.md
odoo/addons/shopfloor_example/services/__init__.py
odoo/addons/shopfloor_example/services/partner_service.py
odoo/addons/shopfloor_example/static/description/icon.png
odoo/addons/shopfloor_example/static/description/index.html
odoo/addons/shopfloor_example/static/src/components/detail/detail_partner.esm.js
odoo/addons/shopfloor_example/static/src/demo/demo.example.esm.js
odoo/addons/shopfloor_example/static/src/scenario/checkout.esm.js
odoo/addons/shopfloor_example/static/src/scenario/partner.esm.js
odoo/addons/shopfloor_example/templates/assets.xml
odoo/addons/shopfloor_example/tests/__init__.py
odoo_addon_shopfloor_example-18.0.1.0.0.2.dist-info/METADATA
odoo_addon_shopfloor_example-18.0.1.0.0.2.dist-info/WHEEL
odoo_addon_shopfloor_example-18.0.1.0.0.2.dist-info/top_level.txt
odoo_addon_shopfloor_example-18.0.1.0.0.2.dist-info/RECORD
