Metadata-Version: 2.1
Name: odoo-addon-shopfloor_example
Version: 18.0.1.0.0.2
Requires-Python: >=3.10
Requires-Dist: odoo-addon-shopfloor_base==18.0.*
Requires-Dist: odoo-addon-shopfloor_mobile_base==18.0.*
Requires-Dist: odoo-addon-shopfloor_mobile_base_auth_api_key==18.0.*
Requires-Dist: odoo==18.0.*
Summary: Show how to customize the Shopfloor app frontend.
Home-page: https://github.com/OCA/shopfloor-app
License: AGPL-3
Author: Camptocamp, ACSONE, Odoo Community Association (OCA)
Author-email: support@odoo-community.org
Classifier: Programming Language :: Python
Classifier: Framework :: Odoo
Classifier: Framework :: Odoo :: 18.0
Classifier: License :: OSI Approved :: GNU Affero General Public License v3
